arithmagic/__init__.py
arithmagic/core.py
shox_arithmagic-0.1.dist-info/METADATA
shox_arithmagic-0.1.dist-info/WHEEL
shox_arithmagic-0.1.dist-info/top_level.txt
shox_arithmagic-0.1.dist-info/RECORD
