Metadata-Version: 2.4
Name: shox-arithmagic
Version: 0.1
Summary: arithmagic
Requires-Python: >=3.11
Dynamic: description-content-type
Dynamic: requires-python
Dynamic: summary
